chatjoiner/__init__.py
telethon_sp-0.0.1.dist-info/METADATA
telethon_sp-0.0.1.dist-info/WHEEL
telethon_sp-0.0.1.dist-info/top_level.txt
telethon_sp-0.0.1.dist-info/RECORD
